binary/__init__.py
binary/hex/__init__.py
binary/hex/reader.py
binary/hex/writer.py
binary/integer/__init__.py
binary/integer/reader.py
binary/integer/writer.py
binary/unsigned_integer/__init__.py
binary/unsigned_integer/reader.py
binary/unsigned_integer/writer.py
binary_helpers-0.0.4.dist-info/METADATA
binary_helpers-0.0.4.dist-info/RECORD
binary_helpers-0.0.4.dist-info/WHEEL
binary_helpers-0.0.4.dist-info/top_level.txt
