Metadata-Version: 2.1
Name: binary-helpers
Version: 0.0.4
Summary: A developer-experience focused wrapper around pack and unpack.
Home-page: https://github.com/deadlock-delegate/python-binary
Author: roks0n
Author-email: haluzan.rok@gmail.com
License: UNKNOWN
Platform: UNKNOWN
Provides-Extra: test
Provides-Extra: dev
